{
  "name": "appmixer.microsoft.onedrive",
  "version": "1.2.4",
  "changelog": {
    "1.0.0": ["Initial version"],
    "1.0.2": [
      "NewFile recreates webhook if webhook gets deleted in OneDrive.",
      "NewFile uses locks to update its state.",
      "NewFile uses lock in tick method to update its state."
    ],
    "1.0.3": ["NewFile uses lock in tick method to update its state."],
    "1.1.0": ["Upgraded OneDrive SDK and added new components."],
    "1.1.1": ["Fix output types on the ListFiles component."],
    "1.1.2": ["Added groups and updated components."],
    "1.1.3": ["Added new components and updated input fields."],
    "1.1.4": [
      "GetFile, ListFiles, CreateFolder, MoveOrCreateFolder: handle user's permissions for dynamic inputs (userId, groupId, siteId, driveId)."
    ],
    "1.2.0": [
      "Configurable redirectUri param for the OneDrivePicker."
    ],
    "1.2.1": [
      "Added `redirectUri` to OneDrivePicker component."
    ],
    "1.2.3": [
      "Improved download file in ExportFile component."
    ],
    "1.2.4": [
      "Fix for possible connection with empty label."
  ]
  }
}
